alu_32bit.v
module alu_32bit(
input  [31:0] a,
input  [31:0] b,
input  [3:0] alu_sel,
output reg [31:0] out
);

always @(*) begin
    out = 32'b0;   // default assignment

    case(alu_sel)
        4'b0000: out = a & b; 
        4'b0001: out = a | b; 
        4'b0010: out = a ^ b; 
        4'b0011: out = ~(a | b); 
        4'b0100: out = ~(a & b); 
        4'b0101: out = a;   
        4'b0110: out = b;
        4'b0111: out = ~a;  
        4'b1000: out = ~b;
        4'b1001: out = a + b;
        4'b1010: out = a - b;
        4'b1011: out = a << 1;
        4'b1100: out = a >> 1;
        4'b1101: out = $signed(a) >>> 1;
        4'b1110: out = ($signed(a) < $signed(b)) ? 32'b1 : 32'b0;
        4'b1111: out = (a == b) ? 32'b1 : 32'b0;
    endcase
end

endmodule

alu_32bit_tb.v
module alu_32bit_tb;

reg [31:0] a, b;
reg [3:0] alu_sel;
wire [31:0] out;

alu_32bit uut (
    .a(a),
    .b(b),
    .alu_sel(alu_sel),
    .out(out)
);

initial begin
    $dumpfile("tb.vcd");
    $dumpvars(0, alu_32bit_tb);

    // AND
    a = 32'hF0F0F0F0; b = 32'h0F0F0F0F; alu_sel = 4'b0000; #10;

    // OR
    alu_sel = 4'b0001; #10;

    // XOR
    alu_sel = 4'b0010; #10;

    // NOR
    alu_sel = 4'b0011; #10;

    // NAND
    alu_sel = 4'b0100; #10;

    // A
    a = 32'h12345678; b = 32'h87654321; alu_sel = 4'b0101; #10;

    // B
    alu_sel = 4'b0110; #10;

    // NOT A
    alu_sel = 4'b0111; #10;

    // NOT B
    alu_sel = 4'b1000; #10;

    // ADD
    alu_sel = 4'b1001; #10;

    // SUB
    alu_sel = 4'b1010; #10;

    // SHL
    alu_sel = 4'b1011; #10;

    // SHR
    alu_sel = 4'b1100; #10;

    // ARITH SHR
    alu_sel = 4'b1101; #10;

    // SLT
    alu_sel = 4'b1110; #10;

    // EQUAL
    b = 32'h12345678; alu_sel = 4'b1111; #10;
    b = 32'h87654321; #10;

    $finish;
end

endmodule

tb.vcd
$date
	Sun Mar 29 14:14:03 2026
$end
$version
	Icarus Verilog
$end
$timescale
	1s
$end
$scope module alu_32bit_tb $end
$var wire 32 ! out [31:0] $end
$var reg 32 " a [31:0] $end
$var reg 4 # alu_sel [3:0] $end
$var reg 32 $ b [31:0] $end
$scope module uut $end
$var wire 32 % a [31:0] $end
$var wire 4 & alu_sel [3:0] $end
$var wire 32 ' b [31:0] $end
$var reg 32 ( out [31:0] $end
$upscope $end
$upscope $end
$enddefinitions $end
#0
$dumpvars
b0 (
b1111000011110000111100001111 '
b0 &
b11110000111100001111000011110000 %
b1111000011110000111100001111 $
b0 #
b11110000111100001111000011110000 "
b0 !
$end
#10
b11111111111111111111111111111111 !
b11111111111111111111111111111111 (
b1 #
b1 &
#20
b11111111111111111111111111111111 !
b11111111111111111111111111111111 (
b10 #
b10 &
#30
b0 !
b0 (
b11 #
b11 &
#40
b11111111111111111111111111111111 !
b11111111111111111111111111111111 (
b100 #
b100 &
#50
b10010001101000101011001111000 !
b10010001101000101011001111000 (
b101 #
b101 &
b10000111011001010100001100100001 $
b10000111011001010100001100100001 '
b10010001101000101011001111000 "
b10010001101000101011001111000 %
#60
b10000111011001010100001100100001 !
b10000111011001010100001100100001 (
b110 #
b110 &
#70
b11101101110010111010100110000111 !
b11101101110010111010100110000111 (
b111 #
b111 &
#80
b1111000100110101011110011011110 !
b1111000100110101011110011011110 (
b1000 #
b1000 &
#90
b10011001100110011001100110011001 !
b10011001100110011001100110011001 (
b1001 #
b1001 &
#100
b10001010110011110001001101010111 !
b10001010110011110001001101010111 (
b1010 #
b1010 &
#110
b100100011010001010110011110000 !
b100100011010001010110011110000 (
b1011 #
b1011 &
#120
b1001000110100010101100111100 !
b1001000110100010101100111100 (
b1100 #
b1100 &
#130
b1001000110100010101100111100 !
b1001000110100010101100111100 (
b1101 #
b1101 &
#140
b0 !
b0 (
b1110 #
b1110 &
#150
b1 !
b1 (
b1111 #
b1111 &
b10010001101000101011001111000 $
b10010001101000101011001111000 '
#160
b0 !
b0 (
b10000111011001010100001100100001 $
b10000111011001010100001100100001 '
